mcp_teams_server/__init__.py
mcp_teams_server/__main__.py
mcp_teams_server/config.py
mcp_teams_server/teams.py
mseep_mcp_teams_server-1.0.7.dist-info/licenses/LICENSE.txt
mseep_mcp_teams_server-1.0.7.dist-info/licenses/NOTICE
mseep_mcp_teams_server-1.0.7.dist-info/METADATA
mseep_mcp_teams_server-1.0.7.dist-info/WHEEL
mseep_mcp_teams_server-1.0.7.dist-info/entry_points.txt
mseep_mcp_teams_server-1.0.7.dist-info/top_level.txt
mseep_mcp_teams_server-1.0.7.dist-info/RECORD
