Metadata-Version: 2.4
Name: mseep-mcp-teams-server
Version: 1.0.7
Summary: An MCP server implementation for Microsoft Teams integration
Author-email: mseep <support@skydeck.ai>
Maintainer-email: Mariano Alonso Ortiz <marianoao@inditex.com>
License: Apache-2.0
Project-URL: Repository, https://github.com/InditexTech/mcp-teams-server
Project-URL: Issues, https://github.com/InditexTech/mcp-teams-server/issues
Keywords: mcp,llm,automation,Microsoft Teams
Requires-Python: >=3.10
License-File: LICENSE.txt
License-File: NOTICE
Requires-Dist: aiohttp==3.10.11
Requires-Dist: asyncio>=3.4.3
Requires-Dist: botbuilder-core>=4.17.0
Requires-Dist: botbuilder-integration-aiohttp>=4.17.0
Requires-Dist: dotenv>=0.9.9
Requires-Dist: mcp[cli]>=1.12.0
Requires-Dist: msgraph-sdk>=1.37.0
Requires-Dist: multidict>=6.6.3
Dynamic: license-file
